mafs/__init__.py
mafs/file.py
mafs/filesystem.py
mafs/mafs.py
mafs/router.py
mafs-0.2.1.dist-info/LICENSE.txt
mafs-0.2.1.dist-info/METADATA
mafs-0.2.1.dist-info/WHEEL
mafs-0.2.1.dist-info/top_level.txt
mafs-0.2.1.dist-info/RECORD
