Metadata-Version: 2.1
Name: mafs
Version: 0.2.1
Summary: Quickly conjure up virtual fileysystems
Home-page: https://github.com/jedevc/mafs
Author: Justin Chadwell
Author-email: jedevc@gmail.com
License: MIT
Platform: UNKNOWN
Classifier: Development Status :: 3 - Alpha
Classifier: Intended Audience :: Developers
Classifier: License :: OSI Approved :: MIT License
Classifier: Operating System :: POSIX :: Linux
Classifier: Programming Language :: Python :: 3
Classifier: Topic :: Software Development :: Libraries
Classifier: Topic :: System :: Filesystems
Requires-Dist: fusepy
